{"frames": {

"explosion1.png":
{
	"frame": {"x":0,"y":0,"w":59,"h":64},
	"rotated": false,
	"trimmed": false,
	"spriteSourceSize": {"x":0,"y":0,"w":59,"h":64},
	"sourceSize": {"w":59,"h":64}
},
"explosion10.png":
{
	"frame": {"x":59,"y":0,"w":64,"h":64},
	"rotated": false,
	"trimmed": false,
	"spriteSourceSize": {"x":0,"y":0,"w":64,"h":64},
	"sourceSize": {"w":64,"h":64}
},
"explosion11.png":
{
	"frame": {"x":123,"y":0,"w":64,"h":64},
	"rotated": false,
	"trimmed": false,
	"spriteSourceSize": {"x":0,"y":0,"w":64,"h":64},
	"sourceSize": {"w":64,"h":64}
},
"explosion12.png":
{
	"frame": {"x":187,"y":0,"w":64,"h":64},
	"rotated": false,
	"trimmed": false,
	"spriteSourceSize": {"x":0,"y":0,"w":64,"h":64},
	"sourceSize": {"w":64,"h":64}
},
"explosion13.png":
{
	"frame": {"x":251,"y":0,"w":64,"h":64},
	"rotated": false,
	"trimmed": false,
	"spriteSourceSize": {"x":0,"y":0,"w":64,"h":64},
	"sourceSize": {"w":64,"h":64}
},
"explosion14.png":
{
	"frame": {"x":315,"y":0,"w":64,"h":64},
	"rotated": false,
	"trimmed": false,
	"spriteSourceSize": {"x":0,"y":0,"w":64,"h":64},
	"sourceSize": {"w":64,"h":64}
},
"explosion15.png":
{
	"frame": {"x":379,"y":0,"w":64,"h":64},
	"rotated": false,
	"trimmed": false,
	"spriteSourceSize": {"x":0,"y":0,"w":64,"h":64},
	"sourceSize": {"w":64,"h":64}
},
"explosion16.png":
{
	"frame": {"x":443,"y":0,"w":64,"h":64},
	"rotated": false,
	"trimmed": false,
	"spriteSourceSize": {"x":0,"y":0,"w":64,"h":64},
	"sourceSize": {"w":64,"h":64}
},
"explosion2.png":
{
	"frame": {"x":507,"y":0,"w":64,"h":64},
	"rotated": false,
	"trimmed": false,
	"spriteSourceSize": {"x":0,"y":0,"w":64,"h":64},
	"sourceSize": {"w":64,"h":64}
},
"explosion3.png":
{
	"frame": {"x":571,"y":0,"w":64,"h":64},
	"rotated": false,
	"trimmed": false,
	"spriteSourceSize": {"x":0,"y":0,"w":64,"h":64},
	"sourceSize": {"w":64,"h":64}
},
"explosion4.png":
{
	"frame": {"x":635,"y":0,"w":64,"h":64},
	"rotated": false,
	"trimmed": false,
	"spriteSourceSize": {"x":0,"y":0,"w":64,"h":64},
	"sourceSize": {"w":64,"h":64}
},
"explosion5.png":
{
	"frame": {"x":699,"y":0,"w":64,"h":64},
	"rotated": false,
	"trimmed": false,
	"spriteSourceSize": {"x":0,"y":0,"w":64,"h":64},
	"sourceSize": {"w":64,"h":64}
},
"explosion6.png":
{
	"frame": {"x":763,"y":0,"w":64,"h":64},
	"rotated": false,
	"trimmed": false,
	"spriteSourceSize": {"x":0,"y":0,"w":64,"h":64},
	"sourceSize": {"w":64,"h":64}
},
"explosion7.png":
{
	"frame": {"x":827,"y":0,"w":64,"h":64},
	"rotated": false,
	"trimmed": false,
	"spriteSourceSize": {"x":0,"y":0,"w":64,"h":64},
	"sourceSize": {"w":64,"h":64}
},
"explosion8.png":
{
	"frame": {"x":891,"y":0,"w":64,"h":64},
	"rotated": false,
	"trimmed": false,
	"spriteSourceSize": {"x":0,"y":0,"w":64,"h":64},
	"sourceSize": {"w":64,"h":64}
},
"explosion9.png":
{
	"frame": {"x":955,"y":0,"w":64,"h":64},
	"rotated": false,
	"trimmed": false,
	"spriteSourceSize": {"x":0,"y":0,"w":64,"h":64},
	"sourceSize": {"w":64,"h":64}
}},
"meta": {
	"image": "explosion.png",
	"format": "RGBA8888",
	"size": {"w":1019,"h":64},
	"scale": "1"
}
}
